pfd/__init__.py
pfd/files.py
pfd/misc.py
pfd/paralleldownload_module.py
pfd/paralleldownloadcli.py
pfd/validate.py
pfd-0.5.2.dist-info/entry_points.txt
pfd-0.5.2.dist-info/WHEEL
pfd-0.5.2.dist-info/METADATA
pfd-0.5.2.dist-info/RECORD
