Metadata-Version: 2.1
Name: pfd
Version: 0.5.2
Summary: Parallel Fast Downloader
Home-page: https://pypi.org/project/pfd/
Keywords: pfd,cli,downloader,multiprocess,files,fast,requests,Parallel Fast Downloader,Concurrent Fast Downloader
Author: Sumanth
Author-email: sumanthreddystar@gmail.com
Maintainer: Sumanth
Maintainer-email: sumanthreddystar@gmail.com
Requires-Python: >=3.6,<4.0
Classifier: Programming Language :: Python :: 3
Classifier: Programming Language :: Python :: 3.6
Classifier: Programming Language :: Python :: 3.7
Classifier: Programming Language :: Python :: 3.8
Classifier: Programming Language :: Python :: 3.9
Classifier: Programming Language :: Python :: 3.10
Requires-Dist: requests (>=2.5,<3.0)
Project-URL: Bug Tracker, https://github.com/insumanth/pfd/issues
Project-URL: Documentation, https://github.com/insumanth/pfd/blob/main/README.md
Project-URL: Repository, https://github.com/insumanth/pfd
